README.md
setup.py
charlogger/__init__.py
charlogger/logger.py
charlogger.egg-info/PKG-INFO
charlogger.egg-info/SOURCES.txt
charlogger.egg-info/dependency_links.txt
charlogger.egg-info/requires.txt
charlogger.egg-info/top_level.txt