Metadata-Version: 2.1
Name: charlogger
Version: 1.2.1
Summary: A logging library for Python.
Home-page: https://github.com/chaarlottte/charlogger
Author: chaarlottte
